mxops/__init__.py
mxops/__main__.py
mxops/enums.py
mxops/errors.py
mxops/cli/__init__.py
mxops/cli/config_cli.py
mxops/cli/data_cli.py
mxops/cli/execution_cli.py
mxops/cli/main_cli.py
mxops/common/__init__.py
mxops/common/constants.py
mxops/common/providers.py
mxops/config/__init__.py
mxops/config/config.py
mxops/config/utils.py
mxops/data/__init__.py
mxops/data/data_cache.py
mxops/data/execution_data.py
mxops/data/utils.py
mxops/data/migrations/__init__.py
mxops/data/migrations/run.py
mxops/data/migrations/v0_1_0__to__v1_0_0.py
mxops/data/path_versions/__init__.py
mxops/data/path_versions/msc.py
mxops/data/path_versions/v0_1_0.py
mxops/data/path_versions/v1_0_0.py
mxops/execution/__init__.py
mxops/execution/account.py
mxops/execution/msc.py
mxops/execution/network.py
mxops/execution/scene.py
mxops/execution/utils.py
mxops/execution/checks/__init__.py
mxops/execution/checks/base.py
mxops/execution/checks/factory.py
mxops/execution/checks/transactions.py
mxops/execution/steps/__init__.py
mxops/execution/steps/base.py
mxops/execution/steps/factory.py
mxops/execution/steps/msc.py
mxops/execution/steps/setup.py
mxops/execution/steps/smart_contract.py
mxops/execution/steps/token_management.py
mxops/execution/steps/transactions.py
mxops/resources/__init__.py
mxops/resources/default_config.ini
mxops/smart_values/__init__.py
mxops/smart_values/base.py
mxops/smart_values/custom.py
mxops/smart_values/factory.py
mxops/smart_values/mx_sdk.py
mxops/smart_values/native.py
mxops/smart_values/utils.py
mxops/utils/__init__.py
mxops/utils/account_storage.py
mxops/utils/chain_simulator.py
mxops/utils/logger.py
mxops/utils/msc.py
mxops/utils/wallets.py
mxops-3.0.2.dist-info/licenses/LICENSE
mxops-3.0.2.dist-info/METADATA
mxops-3.0.2.dist-info/WHEEL
mxops-3.0.2.dist-info/entry_points.txt
mxops-3.0.2.dist-info/top_level.txt
mxops-3.0.2.dist-info/RECORD
