Metadata-Version: 2.4
Name: mxops
Version: 3.0.2
Summary: Python package to automate MultiversX smart contracts deployment and contract interactions in general
Author: Etienne Wallet
Project-URL: Homepage, https://github.com/Catenscia/MxOps
Keywords: elrond,multiversx,smart-contract,devops,tests
Classifier: Programming Language :: Python :: 3
Classifier: License :: OSI Approved :: MIT License
Classifier: Operating System :: OS Independent
Requires-Python: >=3.10
License-File: LICENSE
Requires-Dist: appdirs~=1.4.4
Requires-Dist: configparser~=7.1.0
Requires-Dist: dateparser>=1.2.1
Requires-Dist: importlib-resources~=6.5.2
Requires-Dist: multiversx-sdk[ledger]~=1.1.0
Requires-Dist: numpy>=2.2.4
Requires-Dist: pyyaml~=6.0.2
Requires-Dist: simpleeval~=1.0.3
Dynamic: license-file
